<?xml version="1.0" encoding="UTF-8"?><record_update table="sys_db_object">
    <sys_db_object action="DELETE">
        <access>public</access>
        <actions_access>false</actions_access>
        <alter_access>false</alter_access>
        <caller_access/>
        <client_scripts_access>false</client_scripts_access>
        <configuration_access>false</configuration_access>
        <create_access>false</create_access>
        <create_access_controls>true</create_access_controls>
        <delete_access>false</delete_access>
        <extension_model/>
        <is_extendable>false</is_extendable>
        <label>Ports List</label>
        <live_feed_enabled>false</live_feed_enabled>
        <name>x_513186_domino_ap_ports_list</name>
        <number_ref/>
        <provider_class/>
        <read_access>true</read_access>
        <scriptable_table>false</scriptable_table>
        <super_class/>
        <sys_class_code/>
        <sys_class_name>sys_db_object</sys_class_name>
        <sys_class_path/>
        <sys_created_by>admin</sys_created_by>
        <sys_created_on>2020-09-14 16:16:47</sys_created_on>
        <sys_id>d7e1e6fc07539410c11df2218c1ed02c</sys_id>
        <sys_mod_count>0</sys_mod_count>
        <sys_name>Ports List</sys_name>
        <sys_package display_value="Domino App" source="x_513186_domino_ap">21e2d540070b5010c11df2218c1ed04b</sys_package>
        <sys_policy/>
        <sys_scope display_value="Domino App">21e2d540070b5010c11df2218c1ed04b</sys_scope>
        <sys_update_name>sys_db_object_d7e1e6fc07539410c11df2218c1ed02c</sys_update_name>
        <sys_updated_by>admin</sys_updated_by>
        <sys_updated_on>2020-09-14 16:16:47</sys_updated_on>
        <update_access>false</update_access>
        <user_role display_value="x_513186_domino_ap.ports_list_user" name="x_513186_domino_ap.ports_list_user">16f1a2fc07539410c11df2218c1ed05a</user_role>
        <ws_access>true</ws_access>
    </sys_db_object>
    <sys_update_version action="INSERT_OR_UPDATE">
        <action>DELETE</action>
        <application display_value="Domino App">21e2d540070b5010c11df2218c1ed04b</application>
        <file_path/>
        <instance_id>b4a6de96db7054904b5c50b6f496193e</instance_id>
        <instance_name>dev104053</instance_name>
        <name>sys_db_object_d7e1e6fc07539410c11df2218c1ed02c</name>
        <payload><![CDATA[<?xml version="1.0" encoding="UTF-8"?><record_update table="sys_db_object"><sys_db_object action="INSERT_OR_UPDATE"><access>public</access><actions_access>false</actions_access><alter_access>false</alter_access><caller_access/><client_scripts_access>false</client_scripts_access><configuration_access>false</configuration_access><create_access>false</create_access><create_access_controls>true</create_access_controls><delete_access>false</delete_access><extension_model/><is_extendable>false</is_extendable><label>Ports List</label><live_feed_enabled>false</live_feed_enabled><name>x_513186_domino_ap_ports_list</name><number_ref/><provider_class/><read_access>true</read_access><scriptable_table>false</scriptable_table><super_class/><sys_class_code/><sys_class_name>sys_db_object</sys_class_name><sys_class_path/><sys_created_by>admin</sys_created_by><sys_created_on>2020-09-14 16:16:47</sys_created_on><sys_id>d7e1e6fc07539410c11df2218c1ed02c</sys_id><sys_mod_count>0</sys_mod_count><sys_name>Ports List</sys_name><sys_package display_value="Domino App" source="x_513186_domino_ap">21e2d540070b5010c11df2218c1ed04b</sys_package><sys_policy/><sys_scope display_value="Domino App">21e2d540070b5010c11df2218c1ed04b</sys_scope><sys_update_name>sys_db_object_d7e1e6fc07539410c11df2218c1ed02c</sys_update_name><sys_updated_by>admin</sys_updated_by><sys_updated_on>2020-09-14 16:16:47</sys_updated_on><update_access>false</update_access><user_role display_value="x_513186_domino_ap.ports_list_user" name="x_513186_domino_ap.ports_list_user">16f1a2fc07539410c11df2218c1ed05a</user_role><ws_access>true</ws_access></sys_db_object></record_update>]]></payload>
        <payload_hash>53263413</payload_hash>
        <record_name>Ports List</record_name>
        <reverted_from/>
        <source>3712dc8a07439410c11df2218c1ed02c</source>
        <source_table>sys_update_set</source_table>
        <state>previous</state>
        <sys_created_by>admin</sys_created_by>
        <sys_created_on>2020-09-14 16:16:48</sys_created_on>
        <sys_id>e6f1e6fc07539410c11df2218c1ed0d6</sys_id>
        <sys_mod_count>0</sys_mod_count>
        <sys_recorded_at>1748d678f010000001</sys_recorded_at>
        <sys_updated_by>admin</sys_updated_by>
        <sys_updated_on>2020-09-14 16:16:48</sys_updated_on>
        <type>Table</type>
        <update_guid>22f1e6fc9c539410eafc64c8f7c981d6</update_guid>
        <update_guid_history>22f1e6fc9c539410eafc64c8f7c981d6:53263413</update_guid_history>
    </sys_update_version>
    <sys_metadata_delete action="INSERT_OR_UPDATE">
        <sys_audit_delete/>
        <sys_class_name>sys_metadata_delete</sys_class_name>
        <sys_created_by>admin</sys_created_by>
        <sys_created_on>2020-09-14 16:17:02</sys_created_on>
        <sys_db_object display_value="" name="sys_db_object">sys_db_object</sys_db_object>
        <sys_id>05807367e43a41f68138345f82482024</sys_id>
        <sys_metadata>d7e1e6fc07539410c11df2218c1ed02c</sys_metadata>
        <sys_mod_count>0</sys_mod_count>
        <sys_name>Ports List</sys_name>
        <sys_package display_value="Domino App" source="x_513186_domino_ap">21e2d540070b5010c11df2218c1ed04b</sys_package>
        <sys_parent/>
        <sys_policy/>
        <sys_scope display_value="Domino App">21e2d540070b5010c11df2218c1ed04b</sys_scope>
        <sys_scope_delete display_value="">534871dd57fc4727a77d1cc641633e59</sys_scope_delete>
        <sys_update_name>sys_db_object_d7e1e6fc07539410c11df2218c1ed02c</sys_update_name>
        <sys_update_version display_value="sys_db_object_d7e1e6fc07539410c11df2218c1ed02c">e6f1e6fc07539410c11df2218c1ed0d6</sys_update_version>
        <sys_updated_by>admin</sys_updated_by>
        <sys_updated_on>2020-09-14 16:17:02</sys_updated_on>
    </sys_metadata_delete>
</record_update>
